README.md
setup.py
pypmml_spark/__init__.py
pypmml_spark/link_pmml4s_jars_into_spark.py
pypmml_spark/score_model.py
pypmml_spark/version.py
pypmml_spark/jars/__init__.py
pypmml_spark/jars/commons-math3-3.6.1.jar
pypmml_spark/jars/commons-text-1.6.jar
pypmml_spark/jars/pmml4s-spark_2.11-0.9.16.jar
pypmml_spark/jars/pmml4s_2.11-0.9.16.jar
pypmml_spark/jars/spray-json_2.11-1.3.5.jar
pypmml_spark2.egg-info/PKG-INFO
pypmml_spark2.egg-info/SOURCES.txt
pypmml_spark2.egg-info/dependency_links.txt
pypmml_spark2.egg-info/requires.txt
pypmml_spark2.egg-info/top_level.txt