Metadata-Version: 2.1
Name: pypmml-spark2
Version: 0.9.16
Summary: Python PMML scoring library for PySpark 2.x as SparkML Transformer
Home-page: https://github.com/autodeployai/pypmml-spark
Author: AutoDeployAI
Author-email: autodeploy.ai@gmail.com
License: Apache License 2.0
Download-URL: https://github.com/autodeployai/pypmml-spark/archive/v0.9.16.tar.gz
Platform: UNKNOWN
Classifier: Development Status :: 4 - Beta
Classifier: Environment :: Console
Classifier: Environment :: Web Environment
Classifier: Intended Audience :: Developers
Classifier: Intended Audience :: System Administrators
Classifier: License :: OSI Approved :: Apache Software License
Classifier: Operating System :: OS Independent
Classifier: Programming Language :: Python :: 2.7
Classifier: Programming Language :: Python :: 3.5
Classifier: Programming Language :: Python :: 3.6
Classifier: Programming Language :: Python :: 3.7
Classifier: Topic :: Scientific/Engineering :: Artificial Intelligence
